aext_panels/__init__.py
aext_panels-0.0.2.dist-info/METADATA
aext_panels-0.0.2.dist-info/WHEEL
aext_panels-0.0.2.dist-info/RECORD
