Metadata-Version: 2.1
Name: aext-panels
Version: 0.0.2
Summary: The aext-panels component of anaconda-toolbox
License-Expression: BSD-3-Clause
